application_example/__init__.py
application_example/example.py
keeepcodingtest_leonardo-0.0.1.dist-info/METADATA
keeepcodingtest_leonardo-0.0.1.dist-info/WHEEL
keeepcodingtest_leonardo-0.0.1.dist-info/top_level.txt
keeepcodingtest_leonardo-0.0.1.dist-info/RECORD
