Metadata-Version: 2.1
Name: keeepcodingtest-leonardo
Version: 0.0.1
Summary: Ejemplo de artefacto
Author: keepcoder
Author-email: kcpypitest@gmail.com
License: UNKNOWN
Platform: UNKNOWN
Requires-Python: >=3.6
Requires-Dist: build
Requires-Dist: twine
